pytest_sourceorder.py
pytest_sourceorder-0.6.0.dist-info/COPYING
pytest_sourceorder-0.6.0.dist-info/METADATA
pytest_sourceorder-0.6.0.dist-info/WHEEL
pytest_sourceorder-0.6.0.dist-info/entry_points.txt
pytest_sourceorder-0.6.0.dist-info/top_level.txt
pytest_sourceorder-0.6.0.dist-info/RECORD
