Metadata-Version: 2.1
Name: pytest-sourceorder
Version: 0.6.0
Summary: Test-ordering plugin for pytest
Home-page: https://pagure.io/python-pytest-sourceorder
Author: Petr Viktorin
Author-email: pviktori@redhat.com
License: GPL
Platform: UNKNOWN
Classifier: Development Status :: 4 - Beta
Classifier: License :: OSI Approved :: GNU General Public License v3 or later (GPLv3+)
Classifier: Operating System :: POSIX
Classifier: Framework :: Pytest
Classifier: Programming Language :: Python
Classifier: Programming Language :: Python :: 2.7
Classifier: Programming Language :: Python :: 3
Classifier: Programming Language :: Python :: 3.6
Classifier: Programming Language :: Python :: 3.7
Classifier: Programming Language :: Python :: 3.8
Classifier: Programming Language :: Python :: 3.9
Classifier: Programming Language :: Python :: 3.10
Classifier: Topic :: Software Development :: Quality Assurance
License-File: COPYING
Requires-Dist: pytest
